aiotopics/__init__.py
aiotopics/aiotopics.py
aiotopics-0.1.0.dist-info/LICENSE
aiotopics-0.1.0.dist-info/METADATA
aiotopics-0.1.0.dist-info/WHEEL
aiotopics-0.1.0.dist-info/top_level.txt
aiotopics-0.1.0.dist-info/RECORD
